{"files":[{"culture":"","installRoot":"","ngen":null,"path":"D:\\Projects\\GENFrameWork\\Utilities\\VStudio Extensions\\Remarks\\obj\\Debug\\Remarks.dll","targetPath":"","vsixSubPath":""},{"culture":"","installRoot":"","ngen":null,"path":"D:\\Projects\\GENFrameWork\\Utilities\\VStudio Extensions\\Remarks\\obj\\Debug\\Remarks.pkgdef","targetPath":"","vsixSubPath":""},{"culture":"","installRoot":"","ngen":null,"path":"D:\\Projects\\GENFrameWork\\Utilities\\VStudio Extensions\\Remarks\\GENExtensions.ico","targetPath":"","vsixSubPath":""}]}